opentelemetry/instrumentation/_semconv.py
opentelemetry/instrumentation/bootstrap.py
opentelemetry/instrumentation/bootstrap_gen.py
opentelemetry/instrumentation/dependencies.py
opentelemetry/instrumentation/distro.py
opentelemetry/instrumentation/environment_variables.py
opentelemetry/instrumentation/instrumentor.py
opentelemetry/instrumentation/propagators.py
opentelemetry/instrumentation/py.typed
opentelemetry/instrumentation/sqlcommenter_utils.py
opentelemetry/instrumentation/utils.py
opentelemetry/instrumentation/version.py
opentelemetry/instrumentation/auto_instrumentation/__init__.py
opentelemetry/instrumentation/auto_instrumentation/_load.py
opentelemetry/instrumentation/auto_instrumentation/sitecustomize.py
sw_apm_opentelemetry_instrumentation-0.45b0.dist-info/METADATA
sw_apm_opentelemetry_instrumentation-0.45b0.dist-info/WHEEL
sw_apm_opentelemetry_instrumentation-0.45b0.dist-info/entry_points.txt
sw_apm_opentelemetry_instrumentation-0.45b0.dist-info/licenses/LICENSE
sw_apm_opentelemetry_instrumentation-0.45b0.dist-info/RECORD
