Metadata-Version: 2.3
Name: sw-apm-opentelemetry-instrumentation
Version: 0.45b0
Summary: Fork of Instrumentation Tools & Auto Instrumentation for OpenTelemetry Python
Project-URL: Homepage, https://github.com/open-telemetry/opentelemetry-python-contrib/tree/main/opentelemetry-instrumentation
Author-email: OpenTelemetry Authors <cncf-opentelemetry-contributors@lists.cncf.io>
License-Expression: Apache-2.0
License-File: LICENSE
Classifier: Development Status :: 4 - Beta
Classifier: Intended Audience :: Developers
Classifier: License :: OSI Approved :: Apache Software License
Classifier: Programming Language :: Python
Classifier: Programming Language :: Python :: 3
Classifier: Programming Language :: Python :: 3.8
Classifier: Programming Language :: Python :: 3.9
Classifier: Programming Language :: Python :: 3.10
Classifier: Programming Language :: Python :: 3.11
Requires-Python: >=3.8
Requires-Dist: opentelemetry-api~=1.4
Requires-Dist: setuptools>=16.0
Requires-Dist: wrapt<2.0.0,>=1.0.0
